Metadata-Version: 2.1
Name: psamm
Version: 1.2.1
Summary: PSAMM metabolic modeling tools
Home-page: https://github.com/zhanglab/psamm
Maintainer: Jon Lund Steffensen
Maintainer-email: jon_steffensen@uri.edu
License: GNU GPLv3+
Classifier: Development Status :: 4 - Beta
Classifier: License :: OSI Approved :: GNU General Public License v3 or later (GPLv3+)
Classifier: Programming Language :: Python :: 3.5
Classifier: Programming Language :: Python :: 3.6
Classifier: Programming Language :: Python :: 3.7
Classifier: Programming Language :: Python :: 3.8
Classifier: Programming Language :: Python :: 3.9
License-File: LICENSE
Requires-Dist: pyyaml (>=4.2b1)
Requires-Dist: six
Requires-Dist: xlsxwriter
Requires-Dist: numpy
Requires-Dist: scipy
Requires-Dist: future
Requires-Dist: pandas
Provides-Extra: docs
Requires-Dist: sphinx ; extra == 'docs'
Requires-Dist: sphinx-rtd-theme ; extra == 'docs'
Requires-Dist: mock ; extra == 'docs'
